formulas/__init__.py
formulas/basic/__init__.py
formulas/basic/three_dimensional/__init__.py
formulas/basic/three_dimensional/cone.py
formulas/basic/three_dimensional/cube.py
formulas/basic/three_dimensional/cylinder.py
formulas/basic/three_dimensional/sphere.py
formulas/basic/two_dimensional/__init__.py
formulas/basic/two_dimensional/circle.py
formulas/basic/two_dimensional/rectangle.py
formulas/basic/two_dimensional/square.py
formulas/basic/two_dimensional/trapezoid.py
formulas/basic/two_dimensional/triangle.py
tests/__init__.py
tests/unit_tests.py
tests/basic/__init__.py
tests/basic/three_dimensional/__init__.py
tests/basic/three_dimensional/test_cone.py
tests/basic/three_dimensional/test_cube.py
tests/basic/three_dimensional/test_cylinder.py
tests/basic/three_dimensional/test_sphere.py
tests/basic/three_dimensional/unit_tests.py
tests/basic/two_dimensional/__init__.py
tests/basic/two_dimensional/test_circle.py
tests/basic/two_dimensional/test_rectangle.py
tests/basic/two_dimensional/test_square.py
tests/basic/two_dimensional/test_trapezoid.py
tests/basic/two_dimensional/test_triangle.py
tests/basic/two_dimensional/unit_tests.py
formula_bin-0.1.1.dist-info/METADATA
formula_bin-0.1.1.dist-info/WHEEL
formula_bin-0.1.1.dist-info/top_level.txt
formula_bin-0.1.1.dist-info/RECORD
